spacymoji/__init__.py
spacymoji/tests/__init__.py
spacymoji/tests/test_emoji.py
spacymoji-3.1.0.dist-info/LICENSE
spacymoji-3.1.0.dist-info/METADATA
spacymoji-3.1.0.dist-info/WHEEL
spacymoji-3.1.0.dist-info/entry_points.txt
spacymoji-3.1.0.dist-info/top_level.txt
spacymoji-3.1.0.dist-info/zip-safe
spacymoji-3.1.0.dist-info/RECORD
